pylast/__init__.py
pylast/_version.py
pylast/py.typed
pylast-7.0.2.dist-info/METADATA
pylast-7.0.2.dist-info/WHEEL
pylast-7.0.2.dist-info/licenses/LICENSE.txt
pylast-7.0.2.dist-info/RECORD
