Metadata-Version: 2.4
Name: pylast
Version: 7.0.2
Summary: A Python interface to Last.fm and Libre.fm
Project-URL: Changelog, https://github.com/pylast/pylast/releases
Project-URL: Homepage, https://github.com/pylast/pylast
Project-URL: Source, https://github.com/pylast/pylast
Author-email: "Amr Hassan <amr.hassan@gmail.com> and Contributors" <amr.hassan@gmail.com>
Maintainer: Hugo van Kemenade
License-Expression: Apache-2.0
License-File: LICENSE.txt
Keywords: Last.fm,music,scrobble,scrobbling
Classifier: Development Status :: 5 - Production/Stable
Classifier: Programming Language :: Python :: 3 :: Only
Classifier: Programming Language :: Python :: 3.10
Classifier: Programming Language :: Python :: 3.11
Classifier: Programming Language :: Python :: 3.12
Classifier: Programming Language :: Python :: 3.13
Classifier: Programming Language :: Python :: 3.14
Classifier: Programming Language :: Python :: 3.15
Classifier: Programming Language :: Python :: Implementation :: CPython
Classifier: Programming Language :: Python :: Implementation :: PyPy
Classifier: Topic :: Internet
Classifier: Topic :: Multimedia :: Sound/Audio
Classifier: Topic :: Software Development :: Libraries :: Python Modules
Classifier: Typing :: Typed
Requires-Python: >=3.10
Requires-Dist: httpx>=0.26
Provides-Extra: tests
Requires-Dist: flaky; extra == 'tests'
Requires-Dist: pytest-cov; extra == 'tests'
Requires-Dist: pytest-random-order; extra == 'tests'
Requires-Dist: pytest-recording; extra == 'tests'
Requires-Dist: pytest>=9; extra == 'tests'
Requires-Dist: pyyaml; extra == 'tests'
